ALU.v
module ALU(input clk, input [31:0]A, input [31:0]B, input [3:0]op, output reg[31:0] result, output[4:0] status);
    ALU_status stat(result, status);
    always @(posedge clk) begin
        case (op)
            4'b0000:    // ADD
                result <= A + B;
            4'b1000:    // SUB
                result <= A - B;
            4'b0111:    // AND
                result <= A & B;
            4'b0110:    // OR
                result <= A | B;
            4'b0100:    // XOR
                result <= A ^ B;
        endcase
    end
endmodule

module ALU_status(input[31:0] result, output reg [4:0]status)
    always @(result) begin
        status[0] <= (A[31] & B[31]) | ((A[31] | B[31]) & ~result[31]); // carry
        status[1] <= ^result;                       // odd parity result
        status[2] <= ~(|result);                    // zero result
        status[3] <= result[31];                    // negative result
        status[4] <= (A[31] ~^ B[31]) & (result[31] ^ A[31]); // overflow if input sign bits match
    end
endmodule

ALU_tb.v
`timescale 1ns/1ps

`define ADD 4'b0000
`define SUB 4'b1000
`define AND 4'b0111
`define OR 4'b0110
`define XOR 4'b0100

module ALU_tb();
    reg[31:0] A, B;
    reg[3:0] AluOp;
    reg clk;

    wire[31:0] result;
    wire[4:0] status;

    // input clk, input [31:0]A, input [31:0]B, input [3:0]op, output reg [31:0]result, output reg [4:0]status
    ALU alu(.clk(clk), .A(A), .B(B), .op(AluOp), .result(result), .status(status));

    always begin
        #5 clk <= ~clk;
    end

    initial begin
        $dumpfile("build/ALU.vcd");
        $dumpvars(0, ALU_tb);
        clk <= 0;
        #15;
        A <= 9;
        B <= 10;
        AluOp <= `ADD;
        #15;
        AluOp <= `SUB;
        #15;
        A <= 10;
        #15;
        A <= 1;
        B <= 1;
        AluOp <= `AND;
        #20;
        $stop;
    end

endmodule

build/ALU.vcd
$date
	Sat Nov  5 17:08:54 2022
$end
$version
	Icarus Verilog
$end
$timescale
	1ps
$end
$scope module ALU_tb $end
$var wire 5 ! status [4:0] $end
$var wire 32 " result [31:0] $end
$var reg 32 # A [31:0] $end
$var reg 4 $ AluOp [3:0] $end
$var reg 32 % B [31:0] $end
$var reg 1 & clk $end
$scope module alu $end
$var wire 32 ' A [31:0] $end
$var wire 32 ( B [31:0] $end
$var wire 1 & clk $end
$var wire 4 ) op [3:0] $end
$var reg 32 * result [31:0] $end
$var reg 5 + status [4:0] $end
$upscope $end
$upscope $end
$enddefinitions $end
#0
$dumpvars
bx +
bx *
bx )
bx (
bx '
0&
bx %
bx $
bx #
bx "
bx !
$end
#5000
1&
#10000
0&
#15000
bx0 !
bx0 +
b10011 "
b10011 *
1&
b0 $
b0 )
b1010 %
b1010 (
b1001 #
b1001 '
#20000
0&
#25000
b10 !
b10 +
1&
#30000
0&
b1000 $
b1000 )
#35000
b11111111111111111111111111111111 "
b11111111111111111111111111111111 *
1&
#40000
0&
#45000
b11000 !
b11000 +
b0 "
b0 *
1&
b1010 #
b1010 '
#50000
0&
#55000
b100 !
b100 +
1&
#60000
0&
b111 $
b111 )
b1 %
b1 (
b1 #
b1 '
#65000
b1 "
b1 *
1&
#70000
0&
#75000
b10 !
b10 +
1&
