RegFile.v
// 3 read ops [rs1, rs2]x3
// 3 write ops [rd, int]x3

// module RegFile(input clk, input rst, input r, input [4:0]rd, input [4:0]rs2, input [4:0]rs1, input [31:0]din, output reg [31:0]rs1v, output reg [31:0]rs2v);
//     // 32, 32-bit 
//     reg[31:0] mem [31:0];

//     integer i;

//     always @(posedge clk) begin
//         if (rst) begin
//             for(i = 0; i < 32; i = i + 1)
//                 mem[i] <= 0;
//         end
//         else begin
//             if (r) begin
//                 rs1v <= mem[rs1];
//                 rs2v <= mem[rs2];
//             end
//             else
//                 mem[rd] <= din;
//         end
//     end
// endmodule

module RegFile(clk, rst, rd, rs1, rs2, data_in, read, rs1_out, rs2_out);
    input clk, rst, read;
    input[4:0] rd, rs1, rs2;
    input[31:0] data_in;

    output reg[31:0] rs1_out, rs2_out;

    reg[31:0] memory[31:0];
    integer i;

    always @(posedge clk) begin
        if (rst) begin
            for (i = 0; i < 32; i = i + 1)
                memory[i] = 0;
        end
        else begin
            if (read) begin
                rs1_out = memory[rs1];
                rs2_out = memory[rs2];
            end
            else begin
                memory[rd] = data_in;
                rs1_out = 0;
                rs2_out = 0;
            end
        end
    end
endmodule

RegFile_tb.v
`timescale 1ns/1ps

module RegFile_tb();
    reg [31:0] din;
    reg [4:0] rs1, rs2, rd;
    reg r, clk, rst;
    wire [31:0] a, b;

    RegFile rf(.clk(clk), .rst(rst), .read(r), .rs1(rs1), .rs2(rs2), .data_in(din), .rd(rd), .rs1_out(a), .rs2_out(b));

    always begin
        #5 clk <= ~clk;
    end

    initial begin
        $dumpfile("build/RegFile.vcd");
        $dumpvars(0, RegFile_tb);

        clk <= 0;
        rst <= 1; #5 rst <= 0; // reset
        // write 1
        #15 r<=0;
        din <= 500;
        rd <= 5;
        // write 2
        #15 r<=0;
        din <= 50;
        rd <= 11;
        // read 1
        #15 r<=1;
        rs1 <= 5;
        rs2 <= 11;
        // write 3
        #15 r<=0;
        din <= 69;
        rd <= 23;
        // read 2
        #15 r<=1;
        rs1 <= 11;
        rs2 <= 23;
        // read 3
        #15;
        rs1 <= 23;
        rs2 <= 5;
        #15 $stop;
    end
endmodule

build/RegFile.vcd
$date
	Fri Oct 21 23:13:55 2022
$end
$version
	Icarus Verilog
$end
$timescale
	1ps
$end
$scope module RegFile_tb $end
$var wire 32 ! b [31:0] $end
$var wire 32 " a [31:0] $end
$var reg 1 # clk $end
$var reg 32 $ din [31:0] $end
$var reg 1 % r $end
$var reg 5 & rd [4:0] $end
$var reg 5 ' rs1 [4:0] $end
$var reg 5 ( rs2 [4:0] $end
$var reg 1 ) rst $end
$scope module rf $end
$var wire 1 # clk $end
$var wire 32 * data_in [31:0] $end
$var wire 5 + rd [4:0] $end
$var wire 1 % read $end
$var wire 5 , rs1 [4:0] $end
$var wire 5 - rs2 [4:0] $end
$var wire 1 ) rst $end
$var reg 32 . rs1_out [31:0] $end
$var reg 32 / rs2_out [31:0] $end
$var integer 32 0 i [31:0] $end
$upscope $end
$upscope $end
$enddefinitions $end
#0
$dumpvars
bx 0
bx /
bx .
bx -
bx ,
bx +
bx *
1)
bx (
bx '
bx &
x%
bx $
0#
bx "
bx !
$end
#5000
b0 !
b0 /
b0 "
b0 .
0)
1#
#10000
0#
#15000
1#
#20000
0#
b101 &
b101 +
b111110100 $
b111110100 *
0%
#25000
1#
#30000
0#
#35000
1#
b1011 &
b1011 +
b110010 $
b110010 *
#40000
0#
#45000
1#
#50000
0#
b1011 (
b1011 -
b101 '
b101 ,
1%
#55000
b110010 !
b110010 /
b111110100 "
b111110100 .
1#
#60000
0#
#65000
b0 !
b0 /
b0 "
b0 .
1#
b10111 &
b10111 +
b1000101 $
b1000101 *
0%
#70000
0#
#75000
1#
#80000
0#
b10111 (
b10111 -
b1011 '
b1011 ,
1%
#85000
b1000101 !
b1000101 /
b110010 "
b110010 .
1#
#90000
0#
#95000
b111110100 !
b111110100 /
b1000101 "
b1000101 .
1#
b101 (
b101 -
b10111 '
b10111 ,
